{
    "@class": "com.kony.gen.viz.model.component.KVizImage2",
    "DNDConfig": null,
    "__parentReadjusting__": false,
    "_base64_": null,
    "_height_": {
        "type": "string",
        "value": "50%"
    },
    "_left_": {
        "type": "string",
        "value": "0%"
    },
    "_margin_": [
        0,
        0,
        0,
        0
    ],
    "_padding_": [
        0,
        0,
        0,
        0
    ],
    "_skin_": "sf7db8406dc247a6a10c903de8093ec8",
    "_src_": "konymp_wl_edit_black.png",
    "_top_": {
        "type": "string",
        "value": "0%"
    },
    "_width_": {
        "type": "string",
        "value": "50%"
    },
    "canUpdateUI": true,
    "centerx": {
        "type": "string",
        "value": "50%"
    },
    "centery": {
        "type": "string",
        "value": "50%"
    },
    "containerweight": 100,
    "context": {
        "channel": "mobile",
        "formID": "uwu4b2cc0907574667b974e1579fc4b186",
        "platform": "iphone",
        "templateType": "userwidgets",
        "topLevelBox": null
    },
    "id": "imgEdit",
    "imagescalemode": 1,
    "info": null,
    "iscustomlayout": false,
    "isvisible": true,
    "kuid": "dda9287806544ab28b609fba3c0bb165",
    "name": "kony.ui.Image2",
    "parent": "flxEdit",
    "pf": "userwidgetmodel",
    "retaincontentalignment": false,
    "retainflexpositionproperties": false,
    "srcType": 1,
    "wType": "Image",
    "widgetalignment": 5,
    "zindex": 1
}